pythonds3/__init__.py
pythonds3/basic/__init__.py
pythonds3/basic/deque.py
pythonds3/basic/linked_list.py
pythonds3/basic/queue.py
pythonds3/basic/stack.py
pythonds3/graphs/__init__.py
pythonds3/graphs/adjacency_graph.py
pythonds3/intro/__init__.py
pythonds3/intro/oop.py
pythonds3/searching/__init__.py
pythonds3/searching/hash_table.py
pythonds3/sorting/__init__.py
pythonds3/sorting/sorting_algorithms.py
pythonds3/trees/__init__.py
pythonds3/trees/avl_tree.py
pythonds3/trees/binary_heap.py
pythonds3/trees/binary_search_tree.py
pythonds3/trees/binary_tree.py
pythonds3/trees/priority_queue.py
pythonds3-3.1.0.dist-info/LICENSE
pythonds3-3.1.0.dist-info/METADATA
pythonds3-3.1.0.dist-info/WHEEL
pythonds3-3.1.0.dist-info/top_level.txt
pythonds3-3.1.0.dist-info/RECORD
