Metadata-Version: 2.1
Name: pythonds3
Version: 3.1.0
Summary: Data Structures package for Problem Solving with Algorithms and Data Structures using Python
Home-page: https://github.com/psads/pythonds3
Author: Roman Yasinovskyy
Author-email: yasinovskyy@gmail.com
License: GPLv3+
Keywords: Education,Algorithms,Data Structures,Python,Stack,Queue,Tree,Graph
Platform: OS Independent
Classifier: Programming Language :: Python :: 3
Classifier: License :: OSI Approved :: GNU General Public License v3 or later (GPLv3+)
Classifier: Operating System :: OS Independent
Classifier: Intended Audience :: Education
Classifier: Topic :: Education
Classifier: Development Status :: 5 - Production/Stable
Classifier: Environment :: Console
License-File: LICENSE
